aioimport/__init__.py
aioimport/py.typed
LICENSE
aioimport-0.1.5.dist-info/LICENSE
aioimport-0.1.5.dist-info/WHEEL
aioimport-0.1.5.dist-info/METADATA
aioimport-0.1.5.dist-info/RECORD
