Metadata-Version: 2.1
Name: aioimport
Version: 0.1.5
Summary: Asynchronous module import for asyncio
Home-page: https://github.com/rndr/aioimport
License: MIT
Keywords: asyncio,import
Author: rndr
Author-email: rndr@users.noreply.github.com
Requires-Python: >=3.8,<4.0
Classifier: Development Status :: 3 - Alpha
Classifier: Framework :: AsyncIO
Classifier: License :: OSI Approved :: MIT License
Classifier: Operating System :: OS Independent
Classifier: Programming Language :: Python :: 3
Classifier: Programming Language :: Python :: 3.8
Project-URL: Documentation, https://github.com/rndr/aioimport
Project-URL: Repository, https://github.com/rndr/aioimport
